akron/__init__.py
akron/cli.py
akron/exceptions.py
akron/migrations.py
akron/models.py
akron/orm.py
akron/schema.py
akron/utils.py
akron/core/__init__.py
akron/core/base.py
akron/core/mongo_driver.py
akron/core/mysql_driver.py
akron/core/postgres_driver.py
akron/core/sqlite_driver.py
akron-0.3.1.dist-info/LICENSE
akron-0.3.1.dist-info/METADATA
akron-0.3.1.dist-info/WHEEL
akron-0.3.1.dist-info/entry_points.txt
akron-0.3.1.dist-info/top_level.txt
akron-0.3.1.dist-info/RECORD
